robust_deep_learning/__init__.py
robust_deep_learning/calibration.py
robust_deep_learning/detection.py
robust_deep_learning/dismax.py
robust_deep_learning/general.py
robust_deep_learning/isomax.py
robust_deep_learning/isomaxplus.py
robust_deep_learning/scores.py
robust_deep_learning/softmax.py
robust_deep_learning/thresholds.py
robust_deep_learning/uncertainty.py
robust_deep_learning-0.5.0.dist-info/LICENSE
robust_deep_learning-0.5.0.dist-info/METADATA
robust_deep_learning-0.5.0.dist-info/WHEEL
robust_deep_learning-0.5.0.dist-info/top_level.txt
robust_deep_learning-0.5.0.dist-info/RECORD
