Metadata-Version: 2.1
Name: robust-deep-learning
Version: 0.5.0
Summary: The Robust Deep Learning Library
Home-page: https://github.com/dlmacedo/robust-deep-learning
Author: David Macêdo
Author-email: dlm@cin.ufpe.br
License: UNKNOWN
Keywords: pytorch isomax isomax+ dismax
Platform: UNKNOWN
Classifier: Programming Language :: Python :: 3
Classifier: Operating System :: OS Independent
Classifier: License :: OSI Approved :: Apache Software License
Requires-Python: >=3.6
License-File: LICENSE
Requires-Dist: torch (>=1.10)
Requires-Dist: torchvision
Requires-Dist: torchmetrics
Requires-Dist: torchnet
Requires-Dist: numpy
Requires-Dist: pandas
Requires-Dist: scipy
Requires-Dist: scikit-learn
Requires-Dist: matplotlib
Requires-Dist: seaborn
Requires-Dist: tqdm
Requires-Dist: timm
